commitfmt/__init__.py
commitfmt/__main__.py
commitfmt/commitfmt.py
commitfmt-1.0.4.dist-info/METADATA
commitfmt-1.0.4.dist-info/WHEEL
commitfmt-1.0.4.dist-info/entry_points.txt
commitfmt-1.0.4.dist-info/top_level.txt
commitfmt-1.0.4.dist-info/RECORD
