Metadata-Version: 2.4
Name: commitfmt
Version: 1.0.4
Summary: Utility for formatting and verifying the commit message.
Author-email: Mikhael Khrustik <misha@myrt.co>
License: MIT
Keywords: git,hook
Classifier: License :: OSI Approved :: MIT License
Classifier: Development Status :: 5 - Production/Stable
Classifier: Intended Audience :: Developers
Classifier: Programming Language :: Python :: 3.9
Classifier: Programming Language :: Python :: 3.10
Classifier: Programming Language :: Python :: 3.11
Classifier: Programming Language :: Python :: 3.12
Classifier: Programming Language :: Python :: 3.13
Requires-Python: >=3.9
Requires-Dist: commitfmt_windows==0.1.5; sys_platform == "win32"
Requires-Dist: commitfmt_openbsd==0.1.5; sys_platform == "openbsd"
Requires-Dist: commitfmt_freebsd==0.1.5; sys_platform == "freebsd"
Requires-Dist: commitfmt_darwin==0.1.5; sys_platform == "darwin"
Requires-Dist: commitfmt_linux==0.1.5; sys_platform == "linux"
